itembed/__init__.py
itembed/optimization.py
itembed/task.py
itembed/util.py
itembed-0.5.0.dist-info/LICENSE
itembed-0.5.0.dist-info/METADATA
itembed-0.5.0.dist-info/WHEEL
itembed-0.5.0.dist-info/top_level.txt
itembed-0.5.0.dist-info/RECORD
