Metadata-Version: 2.1
Name: itembed
Version: 0.5.0
Summary: word2vec for itemsets
Home-page: https://gitlab.com/jojolebarjos/itembed
Author: Johan Berdat
Author-email: jojolebarjos@gmail.com
License: MIT
Project-URL: Documentation, https://itembed.readthedocs.io/en/stable/
Project-URL: Tracker, https://gitlab.com/jojolebarjos/itembed/-/issues
Keywords: itemset,word2vec,embedding
Platform: UNKNOWN
Classifier: Development Status :: 4 - Beta
Classifier: Intended Audience :: Developers
Classifier: Intended Audience :: Science/Research
Classifier: License :: OSI Approved :: MIT License
Classifier: Operating System :: OS Independent
Classifier: Programming Language :: Python :: 3
Classifier: Programming Language :: Python :: 3 :: Only
Classifier: Programming Language :: Python :: 3.6
Classifier: Programming Language :: Python :: 3.7
Classifier: Programming Language :: Python :: 3.8
Classifier: Programming Language :: Python :: 3.9
Classifier: Topic :: Scientific/Engineering :: Artificial Intelligence
Classifier: Topic :: Scientific/Engineering :: Information Analysis
Classifier: Topic :: Software Development :: Libraries
Classifier: Topic :: Software Development :: Libraries :: Python Modules
Classifier: Topic :: Text Processing :: Linguistic
Classifier: Topic :: Utilities
Requires-Python: >=3.6
Requires-Dist: numba (>=0.34)
Requires-Dist: scipy (>=0.16)
Requires-Dist: tqdm (>=1.0)
